demux/generador_d_demux.v
module generador_d_demux(
    input clk,
    output reg valid,
    output reg [7:0] data
);
    parameter [7:0] COM = 8'hbc,
                    SKP = 8'h1c,
                    STP = 8'hfb,
                    SDP = 8'h5c,
                    END = 8'hfd,
                    IDL = 8'h7c;
    
    initial begin
        @(posedge clk);
        valid <= 1'b1;
        ////////////////////////////////
        data <= COM;
        @(posedge clk);
        data <= COM;
        @(posedge clk);
        data <= COM;
        @(posedge clk);
        data <= COM;
        @(posedge clk);
        ////////////////////////////////
        data <= STP;
        @(posedge clk);
        data <= 8'h01;
        @(posedge clk);
        data <= 8'h02;
        @(posedge clk);
        data <= END;
        @(posedge clk);
        ////////////////////////////////
        data <= COM;
        @(posedge clk);
        data <= COM;
        @(posedge clk);
        data <= COM;
        @(posedge clk);
        data <= COM;
        @(posedge clk);
        ////////////////////////////////
        data <= SKP;
        @(posedge clk);
        data <= SKP;
        @(posedge clk);
        data <= SKP;
        @(posedge clk);
        data <= SKP;
        @(posedge clk);
        ////////////////////////////////
        data <= SKP;
        @(posedge clk);
        data <= SKP;
        @(posedge clk);
        data <= SKP;
        @(posedge clk);
        data <= SKP;
        @(posedge clk);
        ////////////////////////////////
        data <= SKP;
        @(posedge clk);
        data <= SKP;
        @(posedge clk);
        data <= SKP;
        @(posedge clk);
        data <= SKP;
        @(posedge clk);
        ////////////////////////////////
        data <= STP;
        @(posedge clk);
        data <= 8'h03;
        @(posedge clk);
        data <= 8'h04;
        @(posedge clk);
        data <= 8'h05;
        @(posedge clk);
        ////////////////////////////////
        data <= 8'h06;
        @(posedge clk);
        data <= 8'h07;
        @(posedge clk);
        data <= 8'h08;
        @(posedge clk);
        data <= 8'h09;
        @(posedge clk);
        ////////////////////////////////
        data <= 8'h0A;
        @(posedge clk);
        data <= 8'h0B;
        @(posedge clk);
        data <= 8'h0C;
        @(posedge clk);
        data <= END;
        @(posedge clk);
        ////////////////////////////////
        data <= SDP;
        @(posedge clk);
        data <= 8'h0D;
        @(posedge clk);
        data <= 8'h0E;
        @(posedge clk);
        data <= END;
        @(posedge clk);
        ////////////////////////////////
        data <= IDL;
        @(posedge clk);
        data <= IDL;
        @(posedge clk);
        data <= IDL;
        @(posedge clk);
        data <= IDL;
        @(posedge clk);
        ////////////////////////////////
        data <= IDL;
        @(posedge clk);
        data <= IDL;
        @(posedge clk);
        data <= IDL;
        @(posedge clk);
        data <= IDL;
        @(posedge clk);
        ////////////////////////////////

    $finish;
    end
endmodule

demux/prueba_demux.v
`timescale 	1ns / 1ps

module prueba_demux (
    input [7:0] control,
    input [7:0] data_dm,
    output reg valid,
    output reg [7:0] data,
    output reg clk_1m,
    output reg clk_250k
);
    parameter [7:0] COM = 8'hbc,
                    SKP = 8'h1c,
                    STP = 8'hfb,
                    SDP = 8'h5c,
                    END = 8'hfd,
                    IDL = 8'h7c;

    reg [8*3:0] ctrl;

    initial begin
        $dumpfile("FTM_test.vcd");	// Nombre de archivo del "dump"
        $dumpvars;		          	// Directiva para "dumpear" variables
        $display ("Prueba Demux\n");
        $display ("\t\t\tclk_250k\tValid\tData\t\tDemuxed\t\tControl");
        $monitor($time,"\t%b\t%b\t%b\t%b\t%s",clk_250k, valid, data, data_dm, ctrl);

        ////////////////////////////////
        @(posedge clk_250k);
        valid <= 1'b1;
        ////////////////////////////////
        data <= COM;
        @(posedge clk_250k);
        data <= COM;
        @(posedge clk_250k);
        data <= COM;
        @(posedge clk_250k);
        data <= COM;
        @(posedge clk_250k);
        ////////////////////////////////
        data <= STP;
        @(posedge clk_250k);
        data <= 8'h01;
        @(posedge clk_250k);
        data <= 8'h02;
        @(posedge clk_250k);
        data <= END;
        @(posedge clk_250k);
        ////////////////////////////////
        data <= COM;
        @(posedge clk_250k);
        data <= COM;
        @(posedge clk_250k);
        data <= COM;
        @(posedge clk_250k);
        data <= COM;
        @(posedge clk_250k);
        ////////////////////////////////
        data <= SKP;
        @(posedge clk_250k);
        data <= SKP;
        @(posedge clk_250k);
        data <= SKP;
        @(posedge clk_250k);
        data <= SKP;
        @(posedge clk_250k);
        ////////////////////////////////
        data <= SKP;
        @(posedge clk_250k);
        data <= SKP;
        @(posedge clk_250k);
        data <= SKP;
        @(posedge clk_250k);
        data <= SKP;
        @(posedge clk_250k);
        ////////////////////////////////
        data <= SKP;
        @(posedge clk_250k);
        data <= SKP;
        @(posedge clk_250k);
        data <= SKP;
        @(posedge clk_250k);
        data <= SKP;
        @(posedge clk_250k);
        ////////////////////////////////
        data <= STP;
        @(posedge clk_250k);
        data <= 8'h03;
        @(posedge clk_250k);
        data <= 8'h04;
        @(posedge clk_250k);
        data <= 8'h05;
        @(posedge clk_250k);
        ////////////////////////////////
        data <= 8'h06;
        @(posedge clk_250k);
        data <= 8'h07;
        @(posedge clk_250k);
        data <= 8'h08;
        @(posedge clk_250k);
        data <= 8'h09;
        @(posedge clk_250k);
        ////////////////////////////////
        data <= 8'h0A;
        @(posedge clk_250k);
        data <= 8'h0B;
        @(posedge clk_250k);
        data <= 8'h0C;
        @(posedge clk_250k);
        data <= END;
        @(posedge clk_250k);
        ////////////////////////////////
        data <= SDP;
        @(posedge clk_250k);
        data <= 8'h0D;
        @(posedge clk_250k);
        data <= 8'h0E;
        @(posedge clk_250k);
        data <= END;
        @(posedge clk_250k);
        ////////////////////////////////
        data <= IDL;
        @(posedge clk_250k);
        data <= IDL;
        @(posedge clk_250k);
        data <= IDL;
        @(posedge clk_250k);
        data <= IDL;
        @(posedge clk_250k);
        ////////////////////////////////
        data <= IDL;
        @(posedge clk_250k);
        data <= IDL;
        @(posedge clk_250k);
        data <= IDL;
        @(posedge clk_250k);
        data <= IDL;
        @(posedge clk_250k);
        ////////////////////////////////

        $finish;
    end

    initial	begin
        clk_1m <= 0;			// Valor inicial al reloj, sino siempre será indeterminado
        clk_250k <= 0;    // Valor inicial al reloj, sino siempre será indeterminado
    end

    always	#250 clk_1m <= ~clk_1m; // reloj 1MHz
    always	#1000 clk_250k <= ~clk_250k; // reloj 250kHz

    ///////////////////////////////valor de ctrl
    always @(*) begin
        case (control)
        COM: begin
          ctrl = "COM";
        end
        SKP: begin
          ctrl = "SKP";
        end
        STP: begin
          ctrl = "STP";
        end
        SDP: begin
          ctrl = "SDP";
        end
        END: begin
          ctrl = "END";
        end
        8'b0: begin
          ctrl <= "0";
        end
        default: begin
          ctrl <= "error";
        end
      endcase
    end

endmodule

demux/demux.v
module demux (
  input valid_in,
  input [7:0] data_in,
  input clk,
  output reg [7:0] data_out,
  output reg [7:0] control
  );

  parameter [7:0] COM = 8'hbc,
                  SKP = 8'h1c,
                  STP = 8'hfb,
                  SDP = 8'h5c,
                  END = 8'hfd,
                  IDL = 8'h7c;

  always @(posedge clk) begin
    if (valid_in) begin
      
      case (data_in)
        COM: begin
          control <= COM;
        end
        SKP: begin
          control <= SKP;
        end
        STP: begin
          control <= STP;
        end
        SDP: begin
          control <= SDP;
        end
        END: begin
          control <= END;
        end
        default: begin
          data_out <= data_in;
          control <= 8'b0;
        end
      endcase
      
    end else begin
      data_out <= IDL;
    end
  end

endmodule // demux

mux/tb_demux.v
`include "demux.v"
`include "prueba_demux.v"
`include "generador_d_demux.v"

module tb;

    wire [7:0] D, D_dm, control;
    wire clk_1m, clk_250k, valid;

    demux dm(
        .valid_in(valid),
        .data_in(D),
        .clk(clk_1m),
        .data_out(D_dm),
        .control(control)
    );

    prueba_demux pdm(
        .control(control),
        .data_dm(D_dm),
        .data(D),
        .valid(valid),
        .clk_1m(clk_1m),
        .clk_250k(clk_250k),
    );

    generador_d_demux gdm(
        .clk(clk_250k),
        .valid(valid),
        .data(D)
    );


endmodule

demux/FTM_test.vcd
$date
	Sun May 27 13:29:54 2018
$end
$version
	Icarus Verilog
$end
$timescale
	1ps
$end
$scope module tb $end
$var wire 1 ! valid $end
$var wire 8 " control [7:0] $end
$var wire 1 # clk_250k $end
$var wire 1 $ clk_1m $end
$var wire 8 % D_dm [7:0] $end
$var wire 8 & D [7:0] $end
$scope module dm $end
$var wire 1 ! valid_in $end
$var wire 8 ' data_in [7:0] $end
$var wire 1 $ clk $end
$var reg 8 ( control [7:0] $end
$var reg 8 ) data_out [7:0] $end
$upscope $end
$scope module pdm $end
$var wire 8 * control [7:0] $end
$var wire 8 + data_dm [7:0] $end
$var reg 1 $ clk_1m $end
$var reg 1 # clk_250k $end
$var reg 25 , ctrl [24:0] $end
$var reg 8 - data [7:0] $end
$var reg 1 ! valid $end
$upscope $end
$upscope $end
$enddefinitions $end
#0
$dumpvars
bx -
bx ,
bx +
bx *
bx )
bx (
bx '
bx &
bx %
0$
0#
bx "
x!
$end
#250000
b1111100 %
b1111100 )
b1111100 +
1$
#500000
0$
#750000
1$
#1000000
b10111100 &
b10111100 '
b10111100 -
1!
0$
1#
#1250000
b10000110100111101001101 ,
b10111100 "
b10111100 (
b10111100 *
1$
#1500000
0$
#1750000
1$
#2000000
0$
0#
#2250000
1$
#2500000
0$
#2750000
1$
#3000000
0$
1#
#3250000
1$
#3500000
0$
#3750000
1$
#4000000
0$
0#
#4250000
1$
#4500000
0$
#4750000
1$
#5000000
0$
1#
#5250000
1$
#5500000
0$
#5750000
1$
#6000000
0$
0#
#6250000
1$
#6500000
0$
#6750000
1$
#7000000
0$
1#
#7250000
1$
#7500000
0$
#7750000
1$
#8000000
0$
0#
#8250000
1$
#8500000
0$
#8750000
1$
#9000000
b11111011 &
b11111011 '
b11111011 -
0$
1#
#9250000
b10100110101010001010000 ,
b11111011 "
b11111011 (
b11111011 *
1$
#9500000
0$
#9750000
1$
#10000000
0$
0#
#10250000
1$
#10500000
0$
#10750000
1$
#11000000
b1 &
b1 '
b1 -
0$
1#
#11250000
b110000 ,
b0 "
b0 (
b0 *
b1 %
b1 )
b1 +
1$
#11500000
0$
#11750000
1$
#12000000
0$
0#
#12250000
1$
#12500000
0$
#12750000
1$
#13000000
b10 &
b10 '
b10 -
0$
1#
#13250000
b10 %
b10 )
b10 +
1$
#13500000
0$
#13750000
1$
#14000000
0$
0#
#14250000
1$
#14500000
0$
#14750000
1$
#15000000
b11111101 &
b11111101 '
b11111101 -
0$
1#
#15250000
b10001010100111001000100 ,
b11111101 "
b11111101 (
b11111101 *
1$
#15500000
0$
#15750000
1$
#16000000
0$
0#
#16250000
1$
#16500000
0$
#16750000
1$
#17000000
b10111100 &
b10111100 '
b10111100 -
0$
1#
#17250000
b10000110100111101001101 ,
b10111100 "
b10111100 (
b10111100 *
1$
#17500000
0$
#17750000
1$
#18000000
0$
0#
#18250000
1$
#18500000
0$
#18750000
1$
#19000000
0$
1#
#19250000
1$
#19500000
0$
#19750000
1$
#20000000
0$
0#
#20250000
1$
#20500000
0$
#20750000
1$
#21000000
0$
1#
#21250000
1$
#21500000
0$
#21750000
1$
#22000000
0$
0#
#22250000
1$
#22500000
0$
#22750000
1$
#23000000
0$
1#
#23250000
1$
#23500000
0$
#23750000
1$
#24000000
0$
0#
#24250000
1$
#24500000
0$
#24750000
1$
#25000000
b11100 &
b11100 '
b11100 -
0$
1#
#25250000
b10100110100101101010000 ,
b11100 "
b11100 (
b11100 *
1$
