serdes/SerializadorUv.v
//IE-0523 Circuitos Digitales II
//Proyecto1. Serializadodor del Regitro Desplazable de 8 bits	
//I Ciclo 2018

module serializador(enb,data,clk,out);

	//Entradas // enb =1 palabra valida, enb=0 invalida
	input clk, enb; 
	input [7:0] data;	//	Data
	
	//Variables Temporales / Registros Internos
	reg rst=1;
	reg [7:0] temp;
	reg [3:0] counter;
	
	//Salida
	output reg out;

//Control del Path.
always @(posedge clk or negedge rst ) begin
	if (rst==1) begin
	temp <= data;
	counter <= 4'b0000;
//	counter <= counter + 1'b1;
	end
	//Cuenta de 0 a 8.
	else begin
		out <= temp[7-counter];
		counter <= counter + 1'b1;
		end
	if (counter == 4'b0111) begin
	rst 	<= 1'b1;		// Restaurar la Cuenta.
	counter <= 4'b0000;
	end
	else
		rst = 0;
end

//Data Path.
//always @(posedge clk) begin
	//Datos serializados.
	//out <= temp[counter];
//end

endmodule

serdes/tester1.v
//IE-0523 Circuitos Digitales II
//Proyecto1. Tester de Registro.	
//I Ciclo 2018

//Modulo Tester 
module tester(enb,data,clk,out);
	//Salidas.
	output reg clk,enb;
	output reg [7:0] data;
	input out;

//Señal de Reloj / Frecuencia del reloj
	always #2 clk = !clk;

initial begin
	//Valores Iniciales
	clk =0;
	enb =1;
	
	$display("Inicia Prueba, Cargamos 10001000");
	data = 8'b10001000; // de 8 bits.
	#50; //Retardo
	$finish;
    end
endmodule

serdes/Serializador_tb.v
//IE-0523 Circuitos Digitales II
//Proyecto1. Test Bench del Serializador de 9 bits
//I Ciclo 2018

//Definicion del modulo
module testbench();

wire [7:0] data;
wire enb;
wire out;
wire clk;

//Intanciando Modulos
tester test1(enb,data,clk,out);
serializador ser1(enb,data,clk,out);

//Resultados en Terminal
initial
  begin
    $dumpfile("registro.vcd");
    $dumpvars;
    //$display ("time\t clk enb  data  out");
    //$monitor ("%g\t    %b  %b  %b  %b ");
    //$time(clk, enb, data, out);
    #50 $finish;
  end
endmodule

serdes/registro.vcd
$date
	Wed May 23 10:40:18 2018
$end
$version
	Icarus Verilog
$end
$timescale
	1s
$end
$scope module testbench $end
$var wire 1 ! out $end
$var wire 1 " enb $end
$var wire 8 # data [7:0] $end
$var wire 1 $ clk $end
$scope module ser1 $end
$var wire 1 " enb $end
$var wire 8 % data [7:0] $end
$var wire 1 $ clk $end
$var reg 4 & counter [3:0] $end
$var reg 1 ! out $end
$var reg 1 ' rst $end
$var reg 8 ( temp [7:0] $end
$upscope $end
$scope module test1 $end
$var wire 1 ! out $end
$var reg 1 $ clk $end
$var reg 8 ) data [7:0] $end
$var reg 1 " enb $end
$upscope $end
$upscope $end
$enddefinitions $end
#0
$dumpvars
b10001000 )
bx (
1'
bx &
b10001000 %
0$
b10001000 #
1"
x!
$end
#2
b0 &
b10001000 (
0'
1$
#4
0$
#6
b1 &
1!
1$
#8
0$
#10
b10 &
0!
1$
#12
0$
#14
b11 &
1$
#16
0$
#18
b100 &
1$
#20
0$
#22
b101 &
1!
1$
#24
0$
#26
b110 &
0!
1$
#28
0$
#30
b111 &
1$
#32
0$
#34
1'
b0 &
1$
#36
0$
#38
0'
1$
#40
0$
#42
b1 &
1!
1$
#44
0$
#46
b10 &
0!
1$
#48
0$
#50
b11 &
1$
